[{"started_at":1778651008,"from":"Ulica Ivana Cankara 17, 10109 Zagreb, Croatia","to":"Mandaličina Ulica 12b, 10000 Zagreb, Croatia","distance_km":1.4,"energy_kwh":0.36,"start_bat":69,"end_bat":69},{"started_at":1778650374,"from":"Mandaličina Ulica 12b, 10000 Zagreb, Croatia","to":"Ulica Ivana Cankara 17, 10109 Zagreb, Croatia","distance_km":1.5,"energy_kwh":0.5,"start_bat":70,"end_bat":69},{"started_at":1778608852,"from":"Mandaličina Ulica 12b, 10000 Zagreb, Croatia","to":"Mandaličina Ulica 12b, 10000 Zagreb, Croatia","distance_km":0.0,"energy_kwh":0.1,"start_bat":42,"end_bat":42},{"started_at":1778608502,"from":"Novomarofska Ulica, 10110 Zagreb, Croatia","to":"Mandaličina Ulica 12b, 10000 Zagreb, Croatia","distance_km":1.9,"energy_kwh":0.62,"start_bat":43,"end_bat":42},{"started_at":1778597564,"from":"Trakošćanska Ulica 30, 10110 Grad Zagreb, Croatia","to":"Novomarofska Ulica, 10110 Zagreb, Croatia","distance_km":0.3,"energy_kwh":0.14,"start_bat":44,"end_bat":44}]